word_neo4j/__init__.py
word_neo4j/send_notification.py
word_neo4j/settings_accessor.py
word_neo4j/test.py
word_neo4j/word_neo4j.py
word_neo4j-1.0.5.dist-info/AUTHORS.rst
word_neo4j-1.0.5.dist-info/LICENSE
word_neo4j-1.0.5.dist-info/METADATA
word_neo4j-1.0.5.dist-info/WHEEL
word_neo4j-1.0.5.dist-info/top_level.txt
word_neo4j-1.0.5.dist-info/RECORD
