Metadata-Version: 2.1
Name: word-neo4j
Version: 1.0.5
Summary: Word Neo4j contains modules relating to word components of Neo4j Cypher queries'
Home-page: https://github.com/kruegg21/word_neo4j
Author: Kurt Bergen Ruegg
Author-email: kurtruegg92@gmail.com
License: MIT license
Keywords: word_neo4j
Platform: UNKNOWN
Classifier: Development Status :: 2 - Pre-Alpha
Classifier: Intended Audience :: Developers
Classifier: License :: OSI Approved :: MIT License
Classifier: Natural Language :: English
Classifier: Programming Language :: Python :: 2
Classifier: Programming Language :: Python :: 2.7
Classifier: Programming Language :: Python :: 3
Classifier: Programming Language :: Python :: 3.4
Classifier: Programming Language :: Python :: 3.5
Classifier: Programming Language :: Python :: 3.6
Classifier: Programming Language :: Python :: 3.7
